weberWinSV/CCheckStdoutRestart.py
weberWinSV/CRepeatRunForWeb.py
weberWinSV/CRunSupervisor.py
weberWinSV/CWebSupervisor.py
weberWinSV/CWinSVProgram.py
weberWinSV/CWinSupervisor.py
weberWinSV/RunSleep.py
weberWinSV/__init__.py
weberWinSV/__main__.py
weberWinSV/demoSettingsWinSV.py
weberWinSV/winsvFuncs.py
weberWinSV-0.0.30.dist-info/LICENSE
weberWinSV-0.0.30.dist-info/METADATA
weberWinSV-0.0.30.dist-info/WHEEL
weberWinSV-0.0.30.dist-info/entry_points.txt
weberWinSV-0.0.30.dist-info/top_level.txt
weberWinSV-0.0.30.dist-info/RECORD
