Metadata-Version: 2.1
Name: weberWinSV
Version: 0.0.30
Summary: Supervisor for Windows wrote by Weber Juche.
Home-page: https://github.com/Weber-JC/PythonEggs/tree/master/weberWinSV
Author: Weber Juche
Author-email: weber.juche@gmail.com
License: MIT
Keywords: Supervisor for Windows weber
Classifier: License :: OSI Approved :: MIT License
Classifier: Programming Language :: Python
Classifier: Intended Audience :: Developers
Classifier: Operating System :: OS Independent
License-File: LICENSE
